mseep_windows_mcp-0.1.0.dist-info/licenses/LICENSE
src/__init__.py
src/desktop/__init__.py
src/desktop/config.py
src/desktop/views.py
src/tree/__init__.py
src/tree/config.py
src/tree/utils.py
src/tree/views.py
mseep_windows_mcp-0.1.0.dist-info/METADATA
mseep_windows_mcp-0.1.0.dist-info/WHEEL
mseep_windows_mcp-0.1.0.dist-info/top_level.txt
mseep_windows_mcp-0.1.0.dist-info/RECORD
