Metadata-Version: 2.4
Name: mseep-windows-mcp
Version: 0.1.0
Summary: Lightweight MCP Server for interacting with Windows Operating System.
Home-page: https://github.com/mseep
Author: mseep
Author-email: support@skydeck.ai
Maintainer: mseep
Maintainer-email: support@skydeck.ai
Keywords: mseep,windows,mcp,ai,desktop,ai agent
Classifier: Programming Language :: Python :: 3
Classifier: License :: OSI Approved :: MIT License
Classifier: Operating System :: OS Independent
Requires-Python: >=3.6
License-File: LICENSE
Requires-Dist: fastmcp>=2.8.1
Requires-Dist: fuzzywuzzy>=0.18.0
Requires-Dist: humancursor>=1.1.5
Requires-Dist: live-inspect>=0.1.1
Requires-Dist: markdownify>=1.1.0
Requires-Dist: pillow>=11.2.1
Requires-Dist: pyautogui>=0.9.54
Requires-Dist: python-levenshtein>=0.27.1
Requires-Dist: requests>=2.32.3
Requires-Dist: uiautomation>=2.0.24
Dynamic: author
Dynamic: author-email
Dynamic: classifier
Dynamic: description
Dynamic: description-content-type
Dynamic: home-page
Dynamic: keywords
Dynamic: license-file
Dynamic: maintainer
Dynamic: maintainer-email
Dynamic: requires-dist
Dynamic: requires-python
Dynamic: summary
